```
Compiled from "HelloByteCode.java"
public class com.qypone.com.qypone.demo.bytecode.HelloByteCode {
  public com.qypone.com.qypone.demo.bytecode.HelloByteCode();
    Code:
       0: aload_0
       1: invokespecial #1                  // Method java/lang/Object."<init>":()V
       4: return

  public static void main(java.lang.String[]);
    Code:
       0: new           #2                  // class com/qypone/learn/bytecode/HelloByteCode
       3: dup
       4: invokespecial #3                  // Method "<init>":()V
       7: astore_1
       8: return
}
```